MANIFEST.in
README.md
requirements.txt
setup.py
contracts/Crowdsale.sol
contracts/HoloToken.sol
contracts/YodaiToken.sol
daconx/__init__.py
daconx/cli.py
daconx/config.py
daconx/extract_extraction_utils.py
daconx/node_traverse.py
daconx/result_extraction.py
daconx/solc_compile.py
daconx/traverse_data_collection.py
daconx/utils.py
daconx.egg-info/PKG-INFO
daconx.egg-info/SOURCES.txt
daconx.egg-info/dependency_links.txt
daconx.egg-info/entry_points.txt
daconx.egg-info/requires.txt
daconx.egg-info/top_level.txt
daconx/models/__init__.py
daconx/models/contract.py
daconx/models/event.py
daconx/models/function.py
daconx/models/id_name.py
daconx/models/modifier.py
daconx/models/parameter.py
daconx/models/state_variable.py
example_results/HoloToken.sol_contract_detailed_data_HoloToken.json
example_results/HoloToken.sol_contract_detailed_data_Ownable.json
example_results/HoloToken.sol_contract_detailed_data_SafeMath.json
example_results/HoloToken.sol_contract_level_data.json