Metadata-Version: 2.1
Name: daconx
Version: 0.1.0
Summary: A tool to collect data for Solidity smart contract for static analysis
Home-page: UNKNOWN
Author: isctae
License: MIT
Keywords: Solidity smart contracts
Platform: UNKNOWN
Requires-Python: >=3.6.0
